Metadata-Version: 2.1
Name: odoo-addon-stock_move_backdating
Version: 17.0.1.0.0.6
Requires-Python: >=3.10
Requires-Dist: odoo>=17.0a,<17.1dev
Summary: Stock Move Backdating
Home-page: https://github.com/OCA/stock-logistics-workflow
License: AGPL-3
Author: Marco Dieckhoff, BREMSKERL, Agile Business Group, Odoo Community Association (OCA)
Author-email: support@odoo-community.org
Classifier: Programming Language :: Python
Classifier: Framework :: Odoo
Classifier: Framework :: Odoo :: 17.0
Classifier: License :: OSI Approved :: GNU Affero General Public License v3
